[{"country":"bw","city":"Aphiri","coordinates":{"lat":"-22.55","long":"27.5333333"}},{"country":"bw","city":"Babusi","coordinates":{"lat":"-24.6780556","long":"25.9169444"}},{"country":"bw","city":"Badiri","coordinates":{"lat":"-24.6538889","long":"25.9158333"}},{"country":"bw","city":"Bahonong","coordinates":{"lat":"-21.9666667","long":"28.3333333"}},{"country":"bw","city":"Baines Drift","coordinates":{"lat":"-22.4833333","long":"28.75"}},{"country":"bw","city":"Bakops","coordinates":{"lat":"-21.0166667","long":"24.3333333"}},{"country":"bw","city":"Bakwena","coordinates":{"lat":"-23.7666667","long":"26.6"}},{"country":"bw","city":"Barachu","coordinates":{"lat":"-23.0166667","long":"21.8166667"}},{"country":"bw","city":"Bebe","coordinates":{"lat":"-19.3833333","long":"22.3333333"}},{"country":"bw","city":"Boatenwana","coordinates":{"lat":"-23.6166667","long":"25.9166667"}},{"country":"bw","city":"Boatlaname","coordinates":{"lat":"-23.6","long":"25.8333333"}},{"country":"bw","city":"Bobonong","coordinates":{"lat":"-21.9666667","long":"28.3333333"}},{"country":"bw","city":"Bogo Gobo","coordinates":{"lat":"-26.65","long":"21.9166667"}},{"country":"bw","city":"Boitshoko","coordinates":{"lat":"-24.6613889","long":"25.9261111"}},{"country":"bw","city":"Bokaa","coordinates":{"lat":"-24.45","long":"26.0166667"}},{"country":"bw","city":"Bokspits","coordinates":{"lat":"-26.9","long":"20.7"}},{"country":"bw","city":"Boleki Village","coordinates":{"lat":"-19.9166667","long":"25.1"}},{"country":"bw","city":"Bonapitse","coordinates":{"lat":"-23.0166667","long":"26.6666667"}},{"country":"bw","city":"Bonapitse Stadt","coordinates":{"lat":"-23.0166667","long":"26.6666667"}},{"country":"bw","city":"Bonapitsi Stadt","coordinates":{"lat":"-23.0166667","long":"26.6666667"}},{"country":"bw","city":"Bontleng","coordinates":{"lat":"-24.6719444","long":"25.9144444"}},{"country":"bw","city":"Bonwapitse","coordinates":{"lat":"-23.0166667","long":"26.6666667"}},{"country":"bw","city":"Borakalalo Camp","coordinates":{"lat":"-24.4","long":"25.5166667"}},{"country":"bw","city":"Borakalalop Camp","coordinates":{"lat":"-24.4","long":"25.5166667"}},{"country":"bw","city":"Borakanelo","coordinates":{"lat":"-24.6591667","long":"25.9161111"}},{"country":"bw","city":"Botie","coordinates":{"lat":"-20.3333333","long":"24.2833333"}},{"country":"bw","city":"Botlapatla","coordinates":{"lat":"-24.0333333","long":"25.5333333"}},{"country":"bw","city":"Botswelelo","coordinates":{"lat":"-24.6566667","long":"25.9233333"}},{"country":"bw","city":"Broadhurst","coordinates":{"lat":"-24.6408333","long":"25.9211111"}},{"country":"bw","city":"Buitsiuang","coordinates":{"lat":"-21.9","long":"21.3833333"}},{"country":"bw","city":"Buitsivango","coordinates":{"lat":"-21.9","long":"21.3833333"}},{"country":"bw","city":"Bulukubalo","coordinates":{"lat":"-24.2333333","long":"23.3166667"}},{"country":"bw","city":"Chichales","coordinates":{"lat":"-19.4166667","long":"22.45"}},{"country":"bw","city":"Chiro Pan","coordinates":{"lat":"-19.4666667","long":"23.9333333"}},{"country":"bw","city":"Chor-he-samuke","coordinates":{"lat":"-20.7333333","long":"24.4166667"}},{"country":"bw","city":"Chuaning","coordinates":{"lat":"-25.55","long":"24.95"}},{"country":"bw","city":"Chuela","coordinates":{"lat":"-23.0166667","long":"27.2166667"}},{"country":"bw","city":"Chukudu Kraal","coordinates":{"lat":"-22.45","long":"23.3833333"}},{"country":"bw","city":"Chuma","coordinates":{"lat":"-20.65","long":"24.9166667"}},{"country":"bw","city":"Damara","coordinates":{"lat":"-20.25","long":"22.4333333"}},{"country":"bw","city":"Dauga","coordinates":{"lat":"-20.7666667","long":"24.4"}},{"country":"bw","city":"Dekar","coordinates":{"lat":"-21.5333333","long":"21.9333333"}},{"country":"bw","city":"Demarara","coordinates":{"lat":"-20.4166667","long":"22.75"}},{"country":"bw","city":"Detoie","coordinates":{"lat":"-21.55","long":"25.6666667"}},{"country":"bw","city":"Dichaobe Ramokwena","coordinates":{"lat":"-18.4833333","long":"21.9833333"}},{"country":"bw","city":"Dichaobe Ramokwenas","coordinates":{"lat":"-18.4833333","long":"21.9833333"}},{"country":"bw","city":"Dilalelo","coordinates":{"lat":"-24.6641667","long":"25.9205556"}},{"country":"bw","city":"Dinokana","coordinates":{"lat":"-22.9166667","long":"27.5666667"}},{"country":"bw","city":"Dirolos","coordinates":{"lat":"-20.1166667","long":"23.1666667"}},{"country":"bw","city":"Ditauana","coordinates":{"lat":"-21.9333333","long":"26.95"}},{"country":"bw","city":"Ditsinane","coordinates":{"lat":"-21.4166667","long":"25.8333333"}},{"country":"bw","city":"Dodo","coordinates":{"lat":"-18.75","long":"25.4"}},{"country":"bw","city":"Dukwe","coordinates":{"lat":"-20.5833333","long":"26.4166667"}},{"country":"bw","city":"Dukwe Quarantine Camp","coordinates":{"lat":"-20.5833333","long":"26.4166667"}},{"country":"bw","city":"Duma","coordinates":{"lat":"-18.75","long":"22.7666667"}},{"country":"bw","city":"Dumadumana","coordinates":{"lat":"-24.5872222","long":"25.8744444"}},{"country":"bw","city":"Dutlwe","coordinates":{"lat":"-23.9833333","long":"23.9"}},{"country":"bw","city":"Dwaha","coordinates":{"lat":"-20.9333333","long":"24.65"}},{"country":"bw","city":"Five Dunes","coordinates":{"lat":"-26.8333333","long":"21.0"}},{"country":"bw","city":"Francistown","coordinates":{"lat":"-21.1666667","long":"27.5166667"}},{"country":"bw","city":"Gabane","coordinates":{"lat":"-24.6666667","long":"25.7822222"}},{"country":"bw","city":"Gaberones Camp","coordinates":{"lat":"-24.6666667","long":"25.9166667"}},{"country":"bw","city":"Gaberones","coordinates":{"lat":"-24.6463889","long":"25.9119444"}},{"country":"bw","city":"Gaberones Village","coordinates":{"lat":"-24.6463889","long":"25.9119444"}},{"country":"bw","city":"Gaborone","coordinates":{"lat":"-24.6463889","long":"25.9119444"}},{"country":"bw","city":"Gadyana Pits","coordinates":{"lat":"-19.7333333","long":"25.25"}},{"country":"bw","city":"Galekgatshwane","coordinates":{"lat":"-24.5191667","long":"25.8075"}},{"country":"bw","city":"Gaphatshwe","coordinates":{"lat":"-24.5738889","long":"25.8341667"}},{"country":"bw","city":"Gaphiri","coordinates":{"lat":"-24.5688889","long":"25.7727778"}},{"country":"bw","city":"Garaditau","coordinates":{"lat":"-24.5105556","long":"25.8411111"}},{"country":"bw","city":"Gehumdi","coordinates":{"lat":"-18.7833333","long":"25.4166667"}},{"country":"bw","city":"Gerufa","coordinates":{"lat":"-19.2","long":"25.95"}},{"country":"bw","city":"Geruf","coordinates":{"lat":"-19.2","long":"25.95"}},{"country":"bw","city":"Ghanzi","coordinates":{"lat":"-21.5666667","long":"21.7833333"}},{"country":"bw","city":"Goa","coordinates":{"lat":"-18.2833333","long":"21.8333333"}},{"country":"bw","city":"Gobojango","coordinates":{"lat":"-21.8166667","long":"28.7833333"}},{"country":"bw","city":"Gobokonkwane","coordinates":{"lat":"-19.5666667","long":"25.5833333"}},{"country":"bw","city":"Gomo","coordinates":{"lat":"-21.1666667","long":"24.5833333"}},{"country":"bw","city":"Gubujango","coordinates":{"lat":"-21.8166667","long":"28.7833333"}},{"country":"bw","city":"Gucta","coordinates":{"lat":"-20.4","long":"25.1"}},{"country":"bw","city":"Gutta","coordinates":{"lat":"-20.7166667","long":"24.9666667"}},{"country":"bw","city":"Gwaraha","coordinates":{"lat":"-20.7666667","long":"24.8333333"}},{"country":"bw","city":"Gweta","coordinates":{"lat":"-20.1833333","long":"25.2333333"}},{"country":"bw","city":"Habangan","coordinates":{"lat":"-20.5666667","long":"27.55"}},{"country":"bw","city":"Horeme","coordinates":{"lat":"-22.5166667","long":"27.4333333"}},{"country":"bw","city":"Hukuntsi","coordinates":{"lat":"-24.0","long":"21.75"}},{"country":"bw","city":"Ikwaka","coordinates":{"lat":"-18.9","long":"22.3666667"}},{"country":"bw","city":"Inkangwe","coordinates":{"lat":"-24.0166667","long":"25.8"}},{"country":"bw","city":"Jakops","coordinates":{"lat":"-21.0333333","long":"24.3666667"}},{"country":"bw","city":"Janeng","coordinates":{"lat":"-25.4166667","long":"25.55"}},{"country":"bw","city":"Joani","coordinates":{"lat":"-20.1333333","long":"24.5"}},{"country":"bw","city":"Joverega","coordinates":{"lat":"-19.1333333","long":"24.25"}},{"country":"bw","city":"Kabakai","coordinates":{"lat":"-21.7166667","long":"21.6833333"}},{"country":"bw","city":"Kabulabula","coordinates":{"lat":"-17.8333333","long":"24.9666667"}},{"country":"bw","city":"Kachikau","coordinates":{"lat":"-18.1666667","long":"24.4666667"}},{"country":"bw","city":"Kai-Kai","coordinates":{"lat":"-19.8833333","long":"21.1333333"}},{"country":"bw","city":"Kakamashe","coordinates":{"lat":"-23.3666667","long":"20.0833333"}},{"country":"bw","city":"Kakhoudi","coordinates":{"lat":"-22.3166667","long":"27.4"}},{"country":"bw","city":"Kakia","coordinates":{"lat":"-24.7833333","long":"23.4"}},{"country":"bw","city":"Kakoaka","coordinates":{"lat":"-18.6666667","long":"24.3666667"}},{"country":"bw","city":"Kakoro","coordinates":{"lat":"-18.9166667","long":"22.7333333"}},{"country":"bw","city":"Kalakamati","coordinates":{"lat":"-20.6333333","long":"27.3"}},{"country":"bw","city":"Kalakshani","coordinates":{"lat":"-21.9","long":"27.4"}},{"country":"bw","city":"Kalamare","coordinates":{"lat":"-22.8666667","long":"26.5"}},{"country":"bw","city":"Kalkfontein","coordinates":{"lat":"-22.1166667","long":"20.9"}},{"country":"bw","city":"Kangaras","coordinates":{"lat":"-18.8166667","long":"22.5833333"}},{"country":"bw","city":"Kang","coordinates":{"lat":"-23.75","long":"22.8333333"}},{"country":"bw","city":"Kanguma","coordinates":{"lat":"-17.9","long":"24.7333333"}},{"country":"bw","city":"Kanye","coordinates":{"lat":"-24.9833333","long":"25.35"}},{"country":"bw","city":"Karaka","coordinates":{"lat":"-21.7833333","long":"21.3833333"}},{"country":"bw","city":"Karamechen","coordinates":{"lat":"-21.6166667","long":"27.75"}},{"country":"bw","city":"Karamechen Stad","coordinates":{"lat":"-21.6166667","long":"27.75"}},{"country":"bw","city":"Kasane","coordinates":{"lat":"-17.8166667","long":"25.15"}},{"country":"bw","city":"Kashiambaras","coordinates":{"lat":"-18.8666667","long":"22.75"}},{"country":"bw","city":"Kasinka","coordinates":{"lat":"-18.2","long":"24.3166667"}},{"country":"bw","city":"Kataba","coordinates":{"lat":"-18.1666667","long":"24.4166667"}},{"country":"bw","city":"Kaunkwankwata","coordinates":{"lat":"-19.7333333","long":"25.6833333"}},{"country":"bw","city":"Kavimba","coordinates":{"lat":"-18.0166667","long":"24.6"}},{"country":"bw","city":"Kgamanes Post","coordinates":{"lat":"-19.55","long":"22.25"}},{"country":"bw","city":"Kgaphamadi","coordinates":{"lat":"-24.5377778","long":"25.9275"}},{"country":"bw","city":"Kgomofatsha","coordinates":{"lat":"-23.2666667","long":"21.7666667"}},{"country":"bw","city":"Khabane","coordinates":{"lat":"-24.6666667","long":"25.7822222"}},{"country":"bw","city":"Khakalashwe","coordinates":{"lat":"-24.7","long":"25.3833333"}},{"country":"bw","city":"Khakhea","coordinates":{"lat":"-24.65","long":"23.5"}},{"country":"bw","city":"Khama","coordinates":{"lat":"-20.05","long":"24.9833333"}},{"country":"bw","city":"Khama Khama","coordinates":{"lat":"-20.05","long":"24.9833333"}},{"country":"bw","city":"Khanyeng","coordinates":{"lat":"-25.9166667","long":"22.5"}},{"country":"bw","city":"Khanzi","coordinates":{"lat":"-21.5666667","long":"21.7833333"}},{"country":"bw","city":"Kharekai","coordinates":{"lat":"-19.85","long":"22.3833333"}},{"country":"bw","city":"Khasabake","coordinates":{"lat":"-20.7","long":"24.4333333"}},{"country":"bw","city":"Khasebake","coordinates":{"lat":"-20.7","long":"24.4333333"}},{"country":"bw","city":"Khemsbok","coordinates":{"lat":"-21.6833333","long":"21.6333333"}},{"country":"bw","city":"Khnaitso","coordinates":{"lat":"-21.75","long":"21.4833333"}},{"country":"bw","city":"Khomodimo","coordinates":{"lat":"-22.7166667","long":"23.8666667"}},{"country":"bw","city":"Khomodimo Village","coordinates":{"lat":"-22.7166667","long":"23.8666667"}},{"country":"bw","city":"Khomo","coordinates":{"lat":"-21.1666667","long":"24.5833333"}},{"country":"bw","city":"Khoti","coordinates":{"lat":"-25.0333333","long":"22.1166667"}},{"country":"bw","city":"Khudumelapye","coordinates":{"lat":"-23.8833333","long":"24.75"}},{"country":"bw","city":"Khuis","coordinates":{"lat":"-26.6666667","long":"21.8333333"}},{"country":"bw","city":"Khutswe","coordinates":{"lat":"-23.3333333","long":"24.4166667"}},{"country":"bw","city":"Ki-e-Wonga","coordinates":{"lat":"-20.3333333","long":"24.3166667"}},{"country":"bw","city":"Kitsuhele","coordinates":{"lat":"-20.5166667","long":"24.4666667"}},{"country":"bw","city":"Kkhobi","coordinates":{"lat":"-21.7666667","long":"27.2"}},{"country":"bw","city":"Kkhoutsa","coordinates":{"lat":"-21.5833333","long":"21.5666667"}},{"country":"bw","city":"Kkhoutsiri","coordinates":{"lat":"-21.4166667","long":"22.0833333"}},{"country":"bw","city":"Kladiba","coordinates":{"lat":"-24.9333333","long":"25.65"}},{"country":"bw","city":"Kobajango","coordinates":{"lat":"-21.8166667","long":"28.7833333"}},{"country":"bw","city":"Kobojango","coordinates":{"lat":"-21.8166667","long":"28.7833333"}},{"country":"bw","city":"Kogu","coordinates":{"lat":"-19.9833333","long":"21.8333333"}},{"country":"bw","city":"Komane","coordinates":{"lat":"-20.2","long":"23.25"}},{"country":"bw","city":"Kopong","coordinates":{"lat":"-24.4833333","long":"25.8833333"}},{"country":"bw","city":"Kopong Villages","coordinates":{"lat":"-24.4833333","long":"25.8833333"}},{"country":"bw","city":"Krombi Pits","coordinates":{"lat":"-19.5","long":"25.0333333"}},{"country":"bw","city":"Kubu A Hachwe","coordinates":{"lat":"-23.3333333","long":"20.3333333"}},{"country":"bw","city":"Kudia Kam","coordinates":{"lat":"-20.05","long":"24.7"}},{"country":"bw","city":"Kudumalapshwe","coordinates":{"lat":"-23.8833333","long":"24.75"}},{"country":"bw","city":"Kudumatsi","coordinates":{"lat":"-23.4","long":"27.0666667"}},{"country":"bw","city":"Kuke","coordinates":{"lat":"-23.3166667","long":"24.4833333"}},{"country":"bw","city":"Kuki","coordinates":{"lat":"-23.3166667","long":"24.4833333"}},{"country":"bw","city":"Kukumane Kraal","coordinates":{"lat":"-23.0166667","long":"24.1833333"}},{"country":"bw","city":"Kuli","coordinates":{"lat":"-23.05","long":"20.0666667"}},{"country":"bw","city":"Kumba Pits","coordinates":{"lat":"-18.7166667","long":"24.6833333"}},{"country":"bw","city":"Kurametse","coordinates":{"lat":"-23.4","long":"27.0666667"}},{"country":"bw","city":"Kurametsi","coordinates":{"lat":"-23.4","long":"27.0666667"}},{"country":"bw","city":"Kwakhanai","coordinates":{"lat":"-21.75","long":"21.2833333"}},{"country":"bw","city":"Kwaraga","coordinates":{"lat":"-20.4166667","long":"24.5"}},{"country":"bw","city":"Kwedia","coordinates":{"lat":"-25.2666667","long":"24.5166667"}},{"country":"bw","city":"Labani","coordinates":{"lat":"-20.25","long":"24.0666667"}},{"country":"bw","city":"Lambeye","coordinates":{"lat":"-17.9666667","long":"24.6333333"}},{"country":"bw","city":"Lechaneng","coordinates":{"lat":"-21.9666667","long":"27.5"}},{"country":"bw","city":"Lechen","coordinates":{"lat":"-22.65","long":"27.2666667"}},{"country":"bw","city":"Lechomos","coordinates":{"lat":"-18.95","long":"22.8333333"}},{"country":"bw","city":"Lefase","coordinates":{"lat":"-18.1666667","long":"24.0666667"}},{"country":"bw","city":"Lefatsis","coordinates":{"lat":"-18.6666667","long":"22.0666667"}},{"country":"bw","city":"Leftka","coordinates":{"lat":"-24.7833333","long":"25.6666667"}},{"country":"bw","city":"Legwe","coordinates":{"lat":"-17.9833333","long":"24.2166667"}},{"country":"bw","city":"Lehututu","coordinates":{"lat":"-23.9666667","long":"21.8666667"}},{"country":"bw","city":"Lehwerane","coordinates":{"lat":"-25.85","long":"22.3333333"}},{"country":"bw","city":"Lekala","coordinates":{"lat":"-22.7833333","long":"27.6166667"}},{"country":"bw","city":"Lelotong","coordinates":{"lat":"-24.6305556","long":"25.7838889"}},{"country":"bw","city":"Lenake","coordinates":{"lat":"-23.75","long":"24.5833333"}},{"country":"bw","city":"Lenchwe Le Tau","coordinates":{"lat":"-24.3833333","long":"25.85"}},{"country":"bw","city":"Lephepe","coordinates":{"lat":"-23.3166667","long":"25.8"}},{"country":"bw","city":"Lesoane","coordinates":{"lat":"-18.0833333","long":"24.4166667"}},{"country":"bw","city":"Lethakane","coordinates":{"lat":"-21.4166667","long":"25.5833333"}},{"country":"bw","city":"Letlaking","coordinates":{"lat":"-24.0666667","long":"25.0333333"}},{"country":"bw","city":"Letlhajweng","coordinates":{"lat":"-24.5352778","long":"25.8841667"}},{"country":"bw","city":"Letlhakane","coordinates":{"lat":"-21.4166667","long":"25.5833333"}},{"country":"bw","city":"Letlhakawe","coordinates":{"lat":"-21.4166667","long":"25.5833333"}},{"country":"bw","city":"Letlhakeng","coordinates":{"lat":"-24.0666667","long":"25.0333333"}},{"country":"bw","city":"Letsili","coordinates":{"lat":"-21.9666667","long":"28.5166667"}},{"country":"bw","city":"Lettertree","coordinates":{"lat":"-20.5","long":"24.4833333"}},{"country":"bw","city":"Levisfontein","coordinates":{"lat":"-19.5833333","long":"21.15"}},{"country":"bw","city":"Likolwalo","coordinates":{"lat":"-20.5","long":"24.4833333"}},{"country":"bw","city":"Linakalablo","coordinates":{"lat":"-23.9166667","long":"25.65"}},{"country":"bw","city":"Lobatse","coordinates":{"lat":"-25.2166667","long":"25.6666667"}},{"country":"bw","city":"Lobatsi","coordinates":{"lat":"-25.2166667","long":"25.6666667"}},{"country":"bw","city":"Lobilos","coordinates":{"lat":"-18.85","long":"22.65"}},{"country":"bw","city":"Lohoklane","coordinates":{"lat":"-21.8833333","long":"25.7666667"}},{"country":"bw","city":"Lokala Drift","coordinates":{"lat":"-23.9833333","long":"26.6833333"}},{"country":"bw","city":"Lokala","coordinates":{"lat":"-23.9833333","long":"26.6833333"}},{"country":"bw","city":"Lokerane","coordinates":{"lat":"-24.8833333","long":"24.6666667"}},{"country":"bw","city":"Lokwabe","coordinates":{"lat":"-24.1666667","long":"21.8333333"}},{"country":"bw","city":"Lolale","coordinates":{"lat":"-24.6333333","long":"23.5166667"}},{"country":"bw","city":"Lothlekane","coordinates":{"lat":"-21.4166667","long":"25.5833333"}},{"country":"bw","city":"Lothlekane Well","coordinates":{"lat":"-21.4166667","long":"25.5833333"}},{"country":"bw","city":"Lotlakani","coordinates":{"lat":"-25.0833333","long":"25.4333333"}},{"country":"bw","city":"Lupani","coordinates":{"lat":"-22.6166667","long":"27.05"}},{"country":"bw","city":"Lutlhe","coordinates":{"lat":"-23.9666667","long":"23.8166667"}},{"country":"bw","city":"Luzwe","coordinates":{"lat":"-23.9833333","long":"23.9"}},{"country":"bw","city":"Maapi","coordinates":{"lat":"-22.7666667","long":"27.3333333"}},{"country":"bw","city":"Mabole","coordinates":{"lat":"-20.1833333","long":"26.0166667"}},{"country":"bw","city":"Mabosi","coordinates":{"lat":"-23.2333333","long":"27.0833333"}},{"country":"bw","city":"Mabosi Stadt","coordinates":{"lat":"-23.2333333","long":"27.0833333"}},{"country":"bw","city":"Mabuli","coordinates":{"lat":"-25.7833333","long":"24.6"}},{"country":"bw","city":"Mabutswe","coordinates":{"lat":"-24.6961111","long":"25.9927778"}},{"country":"bw","city":"Machaakha","coordinates":{"lat":"-25.25","long":"24.0666667"}},{"country":"bw","city":"Machaneng","coordinates":{"lat":"-23.1833333","long":"27.5"}},{"country":"bw","city":"Machaneng","coordinates":{"lat":"-24.9666667","long":"25.2333333"}},{"country":"bw","city":"Machenen","coordinates":{"lat":"-23.1833333","long":"27.5"}},{"country":"bw","city":"Macloutsie","coordinates":{"lat":"-21.5333333","long":"27.4"}},{"country":"bw","city":"Madibeng","coordinates":{"lat":"-24.6461111","long":"25.9161111"}},{"country":"bw","city":"Madinare","coordinates":{"lat":"-21.95","long":"27.6166667"}},{"country":"bw","city":"Madista","coordinates":{"lat":"-21.0333333","long":"25.15"}},{"country":"bw","city":"Maenga","coordinates":{"lat":"-19.4166667","long":"22.3166667"}},{"country":"bw","city":"Magothla","coordinates":{"lat":"-23.5666667","long":"27.0"}},{"country":"bw","city":"Mahalapitsa","coordinates":{"lat":"-22.7833333","long":"27.2166667"}},{"country":"bw","city":"Mahalapye","coordinates":{"lat":"-23.0666667","long":"26.8333333"}},{"country":"bw","city":"Mahalatswe","coordinates":{"lat":"-23.0666667","long":"26.8333333"}},{"country":"bw","city":"Maike","coordinates":{"lat":"-21.9833333","long":"28.1666667"}},{"country":"bw","city":"Maiphatelo","coordinates":{"lat":"-21.95","long":"27.4"}},{"country":"bw","city":"Maiyabane","coordinates":{"lat":"-22.55","long":"26.1833333"}},{"country":"bw","city":"Majana","coordinates":{"lat":"-24.8","long":"25.5833333"}},{"country":"bw","city":"Majaning","coordinates":{"lat":"-25.65","long":"25.0666667"}},{"country":"bw","city":"Makalamabedi","coordinates":{"lat":"-20.3333333","long":"23.8166667"}},{"country":"bw","city":"Makaleng","coordinates":{"lat":"-20.9","long":"27.2833333"}},{"country":"bw","city":"Makgobi's Stad","coordinates":{"lat":"-25.7166667","long":"25.0833333"}},{"country":"bw","city":"Makgobis Stadt","coordinates":{"lat":"-25.7166667","long":"25.0833333"}},{"country":"bw","city":"Makgobistad","coordinates":{"lat":"-25.7166667","long":"25.0833333"}},{"country":"bw","city":"Makkhalo","coordinates":{"lat":"-20.3166667","long":"23.15"}},{"country":"bw","city":"Maklautsi","coordinates":{"lat":"-22.0166667","long":"28.4166667"}},{"country":"bw","city":"Maklauts","coordinates":{"lat":"-22.0166667","long":"28.4166667"}},{"country":"bw","city":"Makoba","coordinates":{"lat":"-23.4833333","long":"27.1166667"}},{"country":"bw","city":"Makome","coordinates":{"lat":"-21.95","long":"27.5666667"}},{"country":"bw","city":"Makoro","coordinates":{"lat":"-22.2","long":"26.55"}},{"country":"bw","city":"Makuba","coordinates":{"lat":"-20.2666667","long":"23.8166667"}},{"country":"bw","city":"Makumbe","coordinates":{"lat":"-20.2666667","long":"24.2666667"}},{"country":"bw","city":"Makvekve","coordinates":{"lat":"-19.9166667","long":"22.2"}},{"country":"bw","city":"Makwa","coordinates":{"lat":"-21.7166667","long":"26.3666667"}},{"country":"bw","city":"Makwata East","coordinates":{"lat":"-23.3166667","long":"27.3166667"}},{"country":"bw","city":"Makwata","coordinates":{"lat":"-23.2833333","long":"27.3"}},{"country":"bw","city":"Malachoona","coordinates":{"lat":"-25.5666667","long":"24.5"}},{"country":"bw","city":"Malaka","coordinates":{"lat":"-22.5166667","long":"27.4166667"}},{"country":"bw","city":"Malake","coordinates":{"lat":"-22.5166667","long":"27.4166667"}},{"country":"bw","city":"Malalaling","coordinates":{"lat":"-25.75","long":"22.6666667"}},{"country":"bw","city":"Malatshi","coordinates":{"lat":"-19.9666667","long":"22.0166667"}},{"country":"bw","city":"Malau","coordinates":{"lat":"-25.2666667","long":"25.35"}},{"country":"bw","city":"Malekaoakkhomos","coordinates":{"lat":"-18.65","long":"22.2666667"}},{"country":"bw","city":"Mampi","coordinates":{"lat":"-18.8166667","long":"22.25"}},{"country":"bw","city":"Mamuno","coordinates":{"lat":"-22.2833333","long":"20.0333333"}},{"country":"bw","city":"Manduyan","coordinates":{"lat":"-21.3333333","long":"27.4"}},{"country":"bw","city":"Manduyan Stad","coordinates":{"lat":"-21.3333333","long":"27.4"}},{"country":"bw","city":"Manyana","coordinates":{"lat":"-23.4","long":"21.7166667"}},{"country":"bw","city":"Manyane","coordinates":{"lat":"-23.4","long":"21.7166667"}},{"country":"bw","city":"Maope","coordinates":{"lat":"-22.2333333","long":"27.25"}},{"country":"bw","city":"Marushela","coordinates":{"lat":"-24.85","long":"24.3666667"}},{"country":"bw","city":"Masame","coordinates":{"lat":"-22.4666667","long":"26.8166667"}},{"country":"bw","city":"Masarwa","coordinates":{"lat":"-19.35","long":"22.8333333"}},{"country":"bw","city":"Maseme","coordinates":{"lat":"-18.75","long":"25.0666667"}},{"country":"bw","city":"Mashendus","coordinates":{"lat":"-19.9166667","long":"23.2833333"}},{"country":"bw","city":"Mashopa","coordinates":{"lat":"-22.9833333","long":"27.4"}},{"country":"bw","city":"Masike","coordinates":{"lat":"-19.25","long":"22.2666667"}},{"country":"bw","city":"Massering","coordinates":{"lat":"-23.2166667","long":"21.8166667"}},{"country":"bw","city":"Massubia","coordinates":{"lat":"-19.4166667","long":"22.25"}},{"country":"bw","city":"Masunga","coordinates":{"lat":"-20.6666667","long":"27.4166667"}},{"country":"bw","city":"Masungas","coordinates":{"lat":"-20.6666667","long":"27.4166667"}},{"country":"bw","city":"Matangwan","coordinates":{"lat":"-21.0333333","long":"27.3166667"}},{"country":"bw","city":"Matangwan Stad","coordinates":{"lat":"-21.0333333","long":"27.3166667"}},{"country":"bw","city":"Matapa","coordinates":{"lat":"-23.1833333","long":"24.6166667"}},{"country":"bw","city":"Matepasane","coordinates":{"lat":"-22.5166667","long":"27.5"}},{"country":"bw","city":"Mathathane","coordinates":{"lat":"-22.2666667","long":"28.75"}},{"country":"bw","city":"Mathobudukwane","coordinates":{"lat":"-24.6","long":"26.4333333"}},{"country":"bw","city":"Mathubudukwane","coordinates":{"lat":"-24.6","long":"26.4333333"}},{"country":"bw","city":"Matima","coordinates":{"lat":"-20.25","long":"24.2333333"}},{"country":"bw","city":"Matlakhotse","coordinates":{"lat":"-23.15","long":"26.8166667"}},{"country":"bw","city":"Matlakola","coordinates":{"lat":"-22.6","long":"27.3666667"}},{"country":"bw","city":"Matlamanyane","coordinates":{"lat":"-19.55","long":"25.95"}},{"country":"bw","city":"Matlopi","coordinates":{"lat":"-23.5833333","long":"26.95"}},{"country":"bw","city":"Maunatlala","coordinates":{"lat":"-22.5666667","long":"27.5666667"}},{"country":"bw","city":"Maun","coordinates":{"lat":"-19.9833333","long":"23.4166667"}},{"country":"bw","city":"Mekomxana","coordinates":{"lat":"-21.0166667","long":"25.6833333"}},{"country":"bw","city":"Melekgon","coordinates":{"lat":"-26.8333333","long":"21.4666667"}},{"country":"bw","city":"Mena-a-Kwena","coordinates":{"lat":"-20.3166667","long":"24.2666667"}},{"country":"bw","city":"Mephato","coordinates":{"lat":"-24.6683333","long":"25.9244444"}},{"country":"bw","city":"Metsematluko","coordinates":{"lat":"-19.7166667","long":"25.7833333"}},{"country":"bw","city":"Metsemotlhaba","coordinates":{"lat":"-24.5513889","long":"25.8030556"}},{"country":"bw","city":"Micawber","coordinates":{"lat":"-23.7333333","long":"26.7"}},{"country":"bw","city":"Mirapene","coordinates":{"lat":"-19.8","long":"23.65"}},{"country":"bw","city":"Mmadinare","coordinates":{"lat":"-21.95","long":"27.6166667"}},{"country":"bw","city":"Mmaraka","coordinates":{"lat":"-24.6616667","long":"25.9058333"}},{"country":"bw","city":"Mmathubudkwane","coordinates":{"lat":"-24.6","long":"26.4333333"}},{"country":"bw","city":"Mmathubudukwane","coordinates":{"lat":"-24.6","long":"26.4333333"}},{"country":"bw","city":"Mmokolodi","coordinates":{"lat":"-24.6961111","long":"25.8011111"}},{"country":"bw","city":"Mmopone","coordinates":{"lat":"-24.5669444","long":"25.8741667"}},{"country":"bw","city":"Mmumoshweu","coordinates":{"lat":"-20.2333333","long":"23.7833333"}},{"country":"bw","city":"Moakhi","coordinates":{"lat":"-25.5833333","long":"25.0833333"}},{"country":"bw","city":"Mochosens","coordinates":{"lat":"-19.85","long":"23.0833333"}},{"country":"bw","city":"Mochudi","coordinates":{"lat":"-24.4166667","long":"26.15"}},{"country":"bw","city":"Mochudi Village","coordinates":{"lat":"-24.4166667","long":"26.15"}},{"country":"bw","city":"Mochumi","coordinates":{"lat":"-20.8333333","long":"27.65"}},{"country":"bw","city":"Mochumi Stad","coordinates":{"lat":"-20.8333333","long":"27.65"}},{"country":"bw","city":"Mochwere","coordinates":{"lat":"-23.4333333","long":"27.1833333"}},{"country":"bw","city":"Moeng","coordinates":{"lat":"-22.6833333","long":"27.6166667"}},{"country":"bw","city":"Mogapi","coordinates":{"lat":"-22.3333333","long":"27.8333333"}},{"country":"bw","city":"Mogapinyana","coordinates":{"lat":"-22.3666667","long":"27.6"}},{"country":"bw","city":"Mogoditsane","coordinates":{"lat":"-24.6269444","long":"25.8655556"}},{"country":"bw","city":"Mogoditshane","coordinates":{"lat":"-24.6269444","long":"25.8655556"}},{"country":"bw","city":"Mogoditshan","coordinates":{"lat":"-24.6788889","long":"25.8133333"}},{"country":"bw","city":"Mohembo","coordinates":{"lat":"-18.3","long":"21.8"}},{"country":"bw","city":"Moijabana","coordinates":{"lat":"-22.4333333","long":"26.4166667"}},{"country":"bw","city":"Moiyabana","coordinates":{"lat":"-22.4333333","long":"26.4166667"}},{"country":"bw","city":"Mojane","coordinates":{"lat":"-25.6166667","long":"25.05"}},{"country":"bw","city":"Mokatani","coordinates":{"lat":"-22.15","long":"25.8666667"}},{"country":"bw","city":"Mokaya","coordinates":{"lat":"-18.9166667","long":"22.7166667"}},{"country":"bw","city":"Mokhapinyana","coordinates":{"lat":"-22.3166667","long":"27.45"}},{"country":"bw","city":"Mokhokhelo","coordinates":{"lat":"-19.6","long":"23.7833333"}},{"country":"bw","city":"Mokhopetsana","coordinates":{"lat":"-24.4166667","long":"25.55"}},{"country":"bw","city":"Mokhopudis","coordinates":{"lat":"-20.2833333","long":"22.4166667"}},{"country":"bw","city":"Mokobeng","coordinates":{"lat":"-22.9833333","long":"27.5833333"}},{"country":"bw","city":"Mokokwane","coordinates":{"lat":"-22.6","long":"27.6"}},{"country":"bw","city":"Mokwatis","coordinates":{"lat":"-19.5833333","long":"23.7333333"}},{"country":"bw","city":"Molepolole","coordinates":{"lat":"-24.4166667","long":"25.5333333"}},{"country":"bw","city":"Molete","coordinates":{"lat":"-22.9333333","long":"27.5833333"}},{"country":"bw","city":"Molibatsi","coordinates":{"lat":"-22.5333333","long":"27.5166667"}},{"country":"bw","city":"Molorosi","coordinates":{"lat":"-22.4333333","long":"26.4166667"}},{"country":"bw","city":"Molusi","coordinates":{"lat":"-20.4","long":"24.3166667"}},{"country":"bw","city":"Monedi","coordinates":{"lat":"-20.15","long":"22.5333333"}},{"country":"bw","city":"Monnatlala","coordinates":{"lat":"-22.5666667","long":"27.5666667"}},{"country":"bw","city":"Mononyane","coordinates":{"lat":"-24.5419444","long":"25.7713889"}},{"country":"bw","city":"Montsadidi","coordinates":{"lat":"-22.5333333","long":"26.8666667"}},{"country":"bw","city":"Mookane","coordinates":{"lat":"-23.7333333","long":"26.6333333"}},{"country":"bw","city":"Mopipi","coordinates":{"lat":"-21.1833333","long":"24.8833333"}},{"country":"bw","city":"Moremaoto","coordinates":{"lat":"-20.2666667","long":"24.2333333"}},{"country":"bw","city":"Moreme","coordinates":{"lat":"-22.5166667","long":"27.4333333"}},{"country":"bw","city":"Morwamotsu","coordinates":{"lat":"-23.9833333","long":"23.0833333"}},{"country":"bw","city":"Mosetse","coordinates":{"lat":"-20.75","long":"26.65"}},{"country":"bw","city":"Moshupa","coordinates":{"lat":"-24.8","long":"25.3833333"}},{"country":"bw","city":"Moshwana","coordinates":{"lat":"-25.3833333","long":"25.3"}},{"country":"bw","city":"Moshwane","coordinates":{"lat":"-25.3833333","long":"25.3"}},{"country":"bw","city":"Mosikobale","coordinates":{"lat":"-21.85","long":"27.0833333"}},{"country":"bw","city":"Mosopa","coordinates":{"lat":"-24.8","long":"25.3833333"}},{"country":"bw","city":"Mosveng","coordinates":{"lat":"-23.0333333","long":"27.1166667"}},{"country":"bw","city":"Motlhatlokho","coordinates":{"lat":"-20.4666667","long":"22.8333333"}},{"country":"bw","city":"Motlotsane","coordinates":{"lat":"-25.45","long":"24.8"}},{"country":"bw","city":"Motloutse","coordinates":{"lat":"-21.5333333","long":"27.4"}},{"country":"bw","city":"Motusi Village","coordinates":{"lat":"-22.2833333","long":"27.3833333"}},{"country":"bw","city":"Moyonda","coordinates":{"lat":"-19.3333333","long":"22.2666667"}},{"country":"bw","city":"Mpechukudu","coordinates":{"lat":"-21.8166667","long":"25.7833333"}},{"country":"bw","city":"Mswazi","coordinates":{"lat":"-20.6","long":"27.2166667"}},{"country":"bw","city":"Mswazi Village","coordinates":{"lat":"-20.6","long":"27.2166667"}},{"country":"bw","city":"Muchenje","coordinates":{"lat":"-17.9666667","long":"24.65"}},{"country":"bw","city":"Muekekle","coordinates":{"lat":"-20.2833333","long":"24.0166667"}},{"country":"bw","city":"Muhembo","coordinates":{"lat":"-18.3","long":"21.8"}},{"country":"bw","city":"Mumungwe","coordinates":{"lat":"-21.9833333","long":"26.4"}},{"country":"bw","city":"Murumush","coordinates":{"lat":"-24.0833333","long":"23.3666667"}},{"country":"bw","city":"Mushu","coordinates":{"lat":"-23.5833333","long":"26.9166667"}},{"country":"bw","city":"Mutinyane","coordinates":{"lat":"-19.2666667","long":"22.25"}},{"country":"bw","city":"Naledi","coordinates":{"lat":"-24.6816667","long":"25.9025"}},{"country":"bw","city":"Nata","coordinates":{"lat":"-20.2166667","long":"26.1833333"}},{"country":"bw","city":"Nekati","coordinates":{"lat":"-20.0833333","long":"26.0166667"}},{"country":"bw","city":"Ngwala","coordinates":{"lat":"-20.4666667","long":"24.5166667"}},{"country":"bw","city":"Ngwezumba","coordinates":{"lat":"-18.45","long":"24.8666667"}},{"country":"bw","city":"Njinga","coordinates":{"lat":"-18.7833333","long":"22.7333333"}},{"country":"bw","city":"Nkoyaphiri","coordinates":{"lat":"-24.6322222","long":"25.8313889"}},{"country":"bw","city":"Nojane","coordinates":{"lat":"-23.1666667","long":"20.2666667"}},{"country":"bw","city":"Nokaneng","coordinates":{"lat":"-19.6666667","long":"22.2666667"}},{"country":"bw","city":"Nokanen","coordinates":{"lat":"-19.6666667","long":"22.2666667"}},{"country":"bw","city":"Nokaning","coordinates":{"lat":"-19.6666667","long":"22.2666667"}},{"country":"bw","city":"Ntabis","coordinates":{"lat":"-20.05","long":"23.3666667"}},{"country":"bw","city":"Nwali","coordinates":{"lat":"-23.0833333","long":"20.2166667"}},{"country":"bw","city":"Nwanaeanoka","coordinates":{"lat":"-18.9","long":"22.6666667"}},{"country":"bw","city":"Odanakumadona","coordinates":{"lat":"-20.8833333","long":"24.75"}},{"country":"bw","city":"Old Palapye","coordinates":{"lat":"-22.5666667","long":"27.3"}},{"country":"bw","city":"Old Tati","coordinates":{"lat":"-21.5166667","long":"27.8"}},{"country":"bw","city":"Olifants Kloof","coordinates":{"lat":"-22.1833333","long":"20.0833333"}},{"country":"bw","city":"Omagaga","coordinates":{"lat":"-20.35","long":"24.3166667"}},{"country":"bw","city":"Omajaha","coordinates":{"lat":"-20.3666667","long":"24.3166667"}},{"country":"bw","city":"Ootsi","coordinates":{"lat":"-25.0166667","long":"25.7333333"}},{"country":"bw","city":"Ootsi Siding","coordinates":{"lat":"-25.0166667","long":"25.7333333"}},{"country":"bw","city":"Oramalai","coordinates":{"lat":"-20.3","long":"24.25"}},{"country":"bw","city":"Orapa","coordinates":{"lat":"-21.2833333","long":"25.3666667"}},{"country":"bw","city":"Otse","coordinates":{"lat":"-25.0166667","long":"25.7333333"}},{"country":"bw","city":"Pala Camp","coordinates":{"lat":"-23.75","long":"26.95"}},{"country":"bw","city":"Palapaye Road","coordinates":{"lat":"-22.55","long":"27.1333333"}},{"country":"bw","city":"Palapshwe","coordinates":{"lat":"-22.5666667","long":"27.3"}},{"country":"bw","city":"Palapye","coordinates":{"lat":"-22.55","long":"27.1333333"}},{"country":"bw","city":"Palapye Road","coordinates":{"lat":"-22.55","long":"27.1333333"}},{"country":"bw","city":"Palatswe","coordinates":{"lat":"-22.55","long":"27.1333333"}},{"country":"bw","city":"Pamashaba","coordinates":{"lat":"-22.4333333","long":"26.7666667"}},{"country":"bw","city":"Pandamatenga","coordinates":{"lat":"-18.2666667","long":"25.65"}},{"country":"bw","city":"Papascheem","coordinates":{"lat":"-22.3166667","long":"25.9"}},{"country":"bw","city":"Paranatungu","coordinates":{"lat":"-18.05","long":"24.2666667"}},{"country":"bw","city":"Penhalonga","coordinates":{"lat":"-21.35","long":"27.6833333"}},{"country":"bw","city":"Pepascheem","coordinates":{"lat":"-22.3166667","long":"25.9"}},{"country":"bw","city":"Pepe","coordinates":{"lat":"-22.1333333","long":"28.6666667"}},{"country":"bw","city":"Phala","coordinates":{"lat":"-23.75","long":"26.95"}},{"country":"bw","city":"Phikwe","coordinates":{"lat":"-22.3","long":"27.0166667"}},{"country":"bw","city":"Phikwe","coordinates":{"lat":"-22.0166667","long":"27.8333333"}},{"country":"bw","city":"Phologolo","coordinates":{"lat":"-24.6516667","long":"25.9258333"}},{"country":"bw","city":"Phukumakahu","coordinates":{"lat":"-20.7","long":"24.4166667"}},{"country":"bw","city":"Pikwe","coordinates":{"lat":"-22.0166667","long":"27.8333333"}},{"country":"bw","city":"Pikwe-Selibe","coordinates":{"lat":"-22.0166667","long":"27.8333333"}},{"country":"bw","city":"Pilane","coordinates":{"lat":"-24.45","long":"26.1333333"}},{"country":"bw","city":"Pilikwe","coordinates":{"lat":"-22.7833333","long":"27.2333333"}},{"country":"bw","city":"Puluhelo","coordinates":{"lat":"-19.7","long":"23.6833333"}},{"country":"bw","city":"Rakops","coordinates":{"lat":"-21.0166667","long":"24.3333333"}},{"country":"bw","city":"Rakuku","coordinates":{"lat":"-19.5166667","long":"23.8666667"}},{"country":"bw","city":"Ramakonami","coordinates":{"lat":"-22.9333333","long":"27.4666667"}},{"country":"bw","city":"Ramaphato","coordinates":{"lat":"-24.7166667","long":"25.5166667"}},{"country":"bw","city":"Rammu","coordinates":{"lat":"-19.9166667","long":"22.65"}},{"country":"bw","city":"Ramokwena's","coordinates":{"lat":"-18.4833333","long":"21.9833333"}},{"country":"bw","city":"Ramotsaodi","coordinates":{"lat":"-19.7833333","long":"22.3333333"}},{"country":"bw","city":"Ramotswa","coordinates":{"lat":"-24.8666667","long":"25.8166667"}},{"country":"bw","city":"Ramoutsa","coordinates":{"lat":"-24.8666667","long":"25.8166667"}},{"country":"bw","city":"Ranku","coordinates":{"lat":"-24.7086111","long":"25.7694444"}},{"country":"bw","city":"Rantsadi","coordinates":{"lat":"-20.0333333","long":"22.5"}},{"country":"bw","city":"Ranwanalenaus","coordinates":{"lat":"-19.5833333","long":"22.7833333"}},{"country":"bw","city":"Ratholo","coordinates":{"lat":"-22.6833333","long":"27.5833333"}},{"country":"bw","city":"Ratolo","coordinates":{"lat":"-22.6833333","long":"27.5833333"}},{"country":"bw","city":"Sadibas","coordinates":{"lat":"-18.9666667","long":"23.0166667"}},{"country":"bw","city":"Salapitos","coordinates":{"lat":"-19.0166667","long":"22.3666667"}},{"country":"bw","city":"Salidiro","coordinates":{"lat":"-18.8","long":"22.4"}},{"country":"bw","city":"Samahala's","coordinates":{"lat":"-19.7","long":"23.6833333"}},{"country":"bw","city":"Samandozis","coordinates":{"lat":"-18.6666667","long":"22.25"}},{"country":"bw","city":"Samusipas","coordinates":{"lat":"-18.7333333","long":"22.3333333"}},{"country":"bw","city":"Sanie","coordinates":{"lat":"-25.4333333","long":"22.9"}},{"country":"bw","city":"Sankauas Kraal","coordinates":{"lat":"-19.8333333","long":"22.25"}},{"country":"bw","city":"Sansake","coordinates":{"lat":"-21.95","long":"28.1833333"}},{"country":"bw","city":"Sapakanes","coordinates":{"lat":"-19.8333333","long":"23.6166667"}},{"country":"bw","city":"Sebe","coordinates":{"lat":"-18.8","long":"25.5166667"}},{"country":"bw","city":"Sebina","coordinates":{"lat":"-20.8666667","long":"27.25"}},{"country":"bw","city":"Sebutu","coordinates":{"lat":"-18.7166667","long":"25.7"}},{"country":"bw","city":"Sefhetla","coordinates":{"lat":"-25.35","long":"25.3666667"}},{"country":"bw","city":"Sefophe","coordinates":{"lat":"-22.1833333","long":"27.9666667"}},{"country":"bw","city":"Segara","coordinates":{"lat":"-20.2333333","long":"25.2666667"}},{"country":"bw","city":"Sehengo","coordinates":{"lat":"-18.2666667","long":"21.7833333"}},{"country":"bw","city":"Sehengos","coordinates":{"lat":"-18.2666667","long":"21.7833333"}},{"country":"bw","city":"Sehithwa","coordinates":{"lat":"-20.4666667","long":"22.7166667"}},{"country":"bw","city":"Sehithwe","coordinates":{"lat":"-20.4666667","long":"22.7166667"}},{"country":"bw","city":"Sekgwa","coordinates":{"lat":"-24.6661111","long":"25.9111111"}},{"country":"bw","city":"Sekhawawa","coordinates":{"lat":"-25.15","long":"25.0833333"}},{"country":"bw","city":"Sekheng","coordinates":{"lat":"-25.25","long":"24.8"}},{"country":"bw","city":"Sekhwawa","coordinates":{"lat":"-25.15","long":"25.0833333"}},{"country":"bw","city":"Sekoma","coordinates":{"lat":"-24.4","long":"23.8833333"}},{"country":"bw","city":"Sekumis Kraal","coordinates":{"lat":"-19.9666667","long":"22.3666667"}},{"country":"bw","city":"Selebi-Pikwe","coordinates":{"lat":"-22.0166667","long":"27.8333333"}},{"country":"bw","city":"Selebi","coordinates":{"lat":"-22.0166667","long":"27.8333333"}},{"country":"bw","city":"Selemela","coordinates":{"lat":"-24.6633333","long":"25.9163889"}},{"country":"bw","city":"Selibe-Phikwe","coordinates":{"lat":"-22.0166667","long":"27.8333333"}},{"country":"bw","city":"Selibe-Pikwe Mine Lease Area","coordinates":{"lat":"-22.0166667","long":"27.8333333"}},{"country":"bw","city":"Selibe","coordinates":{"lat":"-22.0166667","long":"27.8333333"}},{"country":"bw","city":"Selika","coordinates":{"lat":"-23.0166667","long":"27.7666667"}},{"country":"bw","city":"Seluipe","coordinates":{"lat":"-22.05","long":"27.55"}},{"country":"bw","city":"Senikh","coordinates":{"lat":"-23.5666667","long":"25.7833333"}},{"country":"bw","city":"Seokane","coordinates":{"lat":"-22.0333333","long":"27.4166667"}},{"country":"bw","city":"Serokhe","coordinates":{"lat":"-23.05","long":"27.3666667"}},{"country":"bw","city":"Serowe","coordinates":{"lat":"-22.3833333","long":"26.7166667"}},{"country":"bw","city":"Seruli","coordinates":{"lat":"-22.2833333","long":"27.3833333"}},{"country":"bw","city":"Sesaloa","coordinates":{"lat":"-21.6666667","long":"25.7166667"}},{"country":"bw","city":"Sesume","coordinates":{"lat":"-21.0","long":"24.35"}},{"country":"bw","city":"Sevrelela","coordinates":{"lat":"-24.9","long":"24.9166667"}},{"country":"bw","city":"Shadihadi","coordinates":{"lat":"-23.6333333","long":"25.75"}},{"country":"bw","city":"Shakawe","coordinates":{"lat":"-18.3666667","long":"21.85"}},{"country":"bw","city":"Shakawe","coordinates":{"lat":"-23.15","long":"27.1166667"}},{"country":"bw","city":"Shakse","coordinates":{"lat":"-22.4166667","long":"26.7333333"}},{"country":"bw","city":"Shakwe","coordinates":{"lat":"-23.15","long":"27.1166667"}},{"country":"bw","city":"Shaleshanto","coordinates":{"lat":"-19.15","long":"23.9666667"}},{"country":"bw","city":"Shashis","coordinates":{"lat":"-19.9833333","long":"23.4"}},{"country":"bw","city":"Shawila","coordinates":{"lat":"-20.25","long":"27.2666667"}},{"country":"bw","city":"Shawila Village","coordinates":{"lat":"-20.25","long":"27.2666667"}},{"country":"bw","city":"Shoshong","coordinates":{"lat":"-23.0333333","long":"26.5166667"}},{"country":"bw","city":"Shushong","coordinates":{"lat":"-22.95","long":"26.4833333"}},{"country":"bw","city":"Siambiza","coordinates":{"lat":"-18.0166667","long":"23.3166667"}},{"country":"bw","city":"Sihoro","coordinates":{"lat":"-20.4833333","long":"24.5"}},{"country":"bw","city":"Silokwalela","coordinates":{"lat":"-25.05","long":"25.1333333"}},{"country":"bw","city":"Simati","coordinates":{"lat":"-18.15","long":"24.0666667"}},{"country":"bw","city":"Skegau","coordinates":{"lat":"-18.9666667","long":"22.3833333"}},{"country":"bw","city":"Sofala","coordinates":{"lat":"-23.0333333","long":"27.4666667"}},{"country":"bw","city":"Soromesis","coordinates":{"lat":"-19.35","long":"22.25"}},{"country":"bw","city":"Stumkies Dam","coordinates":{"lat":"-26.3666667","long":"20.7"}},{"country":"bw","city":"Sua","coordinates":{"lat":"-20.05","long":"26.2"}},{"country":"bw","city":"Sukwane","coordinates":{"lat":"-20.8333333","long":"24.3666667"}},{"country":"bw","city":"Sunnyside","coordinates":{"lat":"-21.6666667","long":"22.05"}},{"country":"bw","city":"Tagu","coordinates":{"lat":"-20.7333333","long":"24.8666667"}},{"country":"bw","city":"Takachu","coordinates":{"lat":"-22.55","long":"21.9166667"}},{"country":"bw","city":"Tamasane","coordinates":{"lat":"-22.3166667","long":"27.3666667"}},{"country":"bw","city":"Tantebane","coordinates":{"lat":"-20.8833333","long":"27.5833333"}},{"country":"bw","city":"Tau Stadt","coordinates":{"lat":"-22.6833333","long":"27.4666667"}},{"country":"bw","city":"Tau","coordinates":{"lat":"-22.6833333","long":"27.4666667"}},{"country":"bw","city":"Thabatskudu","coordinates":{"lat":"-20.7333333","long":"25.7666667"}},{"country":"bw","city":"Thamaga","coordinates":{"lat":"-24.7166667","long":"25.5333333"}},{"country":"bw","city":"The Mall","coordinates":{"lat":"-24.6580556","long":"25.9158333"}},{"country":"bw","city":"Tikaseoulo","coordinates":{"lat":"-20.2166667","long":"23.2"}},{"country":"bw","city":"Tipa","coordinates":{"lat":"-25.4166667","long":"25.2166667"}},{"country":"bw","city":"Tlabala","coordinates":{"lat":"-22.4833333","long":"26.3166667"}},{"country":"bw","city":"Tlala Mabeli","coordinates":{"lat":"-21.2666667","long":"26.3"}},{"country":"bw","city":"Tlhape","coordinates":{"lat":"-24.5208333","long":"25.9261111"}},{"country":"bw","city":"Tlhapin","coordinates":{"lat":"-23.3166667","long":"21.7333333"}},{"country":"bw","city":"Tlhareseleele","coordinates":{"lat":"-25.4833333","long":"25.6333333"}},{"country":"bw","city":"Tlhareselele","coordinates":{"lat":"-25.4833333","long":"25.6333333"}},{"country":"bw","city":"Tlogoeankwes","coordinates":{"lat":"-19.1166667","long":"23.4166667"}},{"country":"bw","city":"Tlokhoetonnas","coordinates":{"lat":"-19.5166667","long":"22.9666667"}},{"country":"bw","city":"Tlokweng","coordinates":{"lat":"-24.6686111","long":"25.9711111"}},{"country":"bw","city":"Tlopse","coordinates":{"lat":"-22.35","long":"27.65"}},{"country":"bw","city":"Tobane","coordinates":{"lat":"-21.95","long":"27.9"}},{"country":"bw","city":"Tobgat","coordinates":{"lat":"-24.7666667","long":"25.65"}},{"country":"bw","city":"Tonota","coordinates":{"lat":"-21.4833333","long":"27.4833333"}},{"country":"bw","city":"Tonoto","coordinates":{"lat":"-21.4833333","long":"27.4833333"}},{"country":"bw","city":"Toping","coordinates":{"lat":"-21.9333333","long":"28.1"}},{"country":"bw","city":"Toteng","coordinates":{"lat":"-20.3833333","long":"22.95"}},{"country":"bw","city":"Totoru","coordinates":{"lat":"-25.65","long":"25.0166667"}},{"country":"bw","city":"Tsabong","coordinates":{"lat":"-26.05","long":"22.45"}},{"country":"bw","city":"Tsane","coordinates":{"lat":"-24.0333333","long":"21.9"}},{"country":"bw","city":"Tsau","coordinates":{"lat":"-20.15","long":"22.45"}},{"country":"bw","city":"Tsekanyani","coordinates":{"lat":"-19.8833333","long":"26.6166667"}},{"country":"bw","city":"Tshabong","coordinates":{"lat":"-26.05","long":"22.45"}},{"country":"bw","city":"Tshane","coordinates":{"lat":"-24.0333333","long":"21.9"}},{"country":"bw","city":"Tshapatain","coordinates":{"lat":"-20.3666667","long":"25.15"}},{"country":"bw","city":"Tshoroga","coordinates":{"lat":"-20.35","long":"25.1666667"}},{"country":"bw","city":"Tshwane","coordinates":{"lat":"-22.4","long":"22.05"}},{"country":"bw","city":"Tsienyane","coordinates":{"lat":"-21.0166667","long":"24.3333333"}},{"country":"bw","city":"Tsigara","coordinates":{"lat":"-20.3333333","long":"25.8166667"}},{"country":"bw","city":"Tsimo Ea Pula","coordinates":{"lat":"-22.15","long":"26.7833333"}},{"country":"bw","city":"Tsipi","coordinates":{"lat":"-21.8","long":"25.8833333"}},{"country":"bw","city":"Tsitle","coordinates":{"lat":"-23.2333333","long":"25.7166667"}},{"country":"bw","city":"Tsuli Village","coordinates":{"lat":"-19.8833333","long":"26.5166667"}},{"country":"bw","city":"Tubani","coordinates":{"lat":"-24.7666667","long":"24.2333333"}},{"country":"bw","city":"Village","coordinates":{"lat":"-24.6677778","long":"25.9366667"}},{"country":"bw","city":"Vlei","coordinates":{"lat":"-25.1333333","long":"25.4666667"}},{"country":"bw","city":"Wegdraai","coordinates":{"lat":"-25.3333333","long":"23.5"}},{"country":"bw","city":"Werda","coordinates":{"lat":"-25.2666667","long":"23.2833333"}},{"country":"bw","city":"Xhane","coordinates":{"lat":"-20.2333333","long":"25.0666667"}},{"country":"bw","city":"Zuwe","coordinates":{"lat":"-23.05","long":"24.8333333"}}]